Testcases/ram_simple_dp_async_read_512x32/rtl/ram_simple_dp_async_read_512x32.v
module ram_simple_dp_async_read_512x32 (clk, we, read_addr, write_addr, a,b,reset,out_en, dout);
    input clk, we, reset,out_en;
    input [8:0] read_addr, write_addr;
    input [31:0] a,b;
    output reg [31:0] dout;
    
    reg [31:0] ram [511:0];
    reg [8:0] read_addr_reg;
    reg [31:0] c;
    reg [31:0] c_l;
    reg [31:0] b_l;
    reg [31:0] dout_l;
    reg [31:0] dout_l1;

    always@(*) begin
        c = c_l + b_l;
    end

    always@(negedge clk) begin
        if (!reset)
            c_l <= 0;
        else
            c_l <= a;
    end
    always@(negedge clk) begin
        if (!reset)
            b_l <= 0;
        else
            b_l <= b;
    end

    always @(posedge clk)
    begin
        if (we) begin
            ram[write_addr] <= c;
        end
        else
            dout_l <= ram[read_addr];
        // read_addr_reg <= read_addr;
    end

    // assign dout_l = ram[read_addr_reg];

    always@(*) begin
        if (out_en) dout_l1 = dout_l;
    end

    always@(posedge clk) begin
        if(!reset)
            dout <= 0;
        else
            dout <= dout_l1;
    end

    integer i;
    initial
    begin
        for(i = 0; i < 512; i = i + 1)
            ram[i] = 0;
    end

endmodule

Testcases/ram_simple_dp_async_read_512x32/sim/rtl_sim/testbench.sv
`timescale 1ns/1ps

`include "../../rtl/ram_simple_dp_async_read_512x32.v"
`default_nettype none

module testbench;
// ----- Default clock port is added here since benchmark does not contain one -------
	reg [0:0] clk;

	reg [31:0] c_pred=0;
	reg [31:0] a;
	reg [31:0] b;
	reg [0:0] out_en;
	reg [8:0] read_addr;
	reg [0:0] reset;
	reg [0:0] we;
	reg [8:0] write_addr;
	wire [31:0] dout;

// ----- FPGA fabric instanciation -------
	ram_simple_dp_async_read_512x32 FPGA_DUT(.clk(clk),.a(a),.b(b),.out_en(out_en),.read_addr(read_addr),.reset(reset),.we(we),.write_addr(write_addr),.dout(dout)
	);

	initial begin
		clk[0] <= 1'b0;
		while(1) begin
			#1
			clk[0] <= !clk[0];
		end
	end

	initial begin
		$dumpfile("wave.vcd");
		$dumpvars(1, testbench);
	end
// ----- END output waveform to VCD file -------



initial begin
	$timeformat(-9, 2, "ns", 20);
	$display("Simulation start");
// ----- Can be changed by the user for his/her need -------

    we=0; 
    reset=1;
    out_en=0;
    read_addr=0;
    write_addr=0;
    a=0;
    b=0;

    repeat(5) @(negedge clk);
    reset=0;
    repeat(5) @(negedge clk);
    reset=1;
    repeat(10) @(negedge clk);
    a=32'h00000000;
    b=32'h11111111;
    c_pred=a+b;
    // c_pred = data;
    we=1;
    out_en=1;
    repeat(5) @(negedge clk);
    if (dout !== c_pred) begin
        $display("Status: Test Failed: @%0t ADDR: %0d, Expected Data: %0h, Actual Data: %0h", $time, read_addr, c_pred, dout); 
    end
    else begin
        $display("Status: Test Passed: @%0t ADDR: %0d, Expected Data: %0h, Actual Data: %0h", $time, read_addr, c_pred, dout); 
    end 
    repeat(10) @(negedge clk);

    for (int i = 0; i<512; i++) begin
        a = $urandom_range(0, 511);
        b = $urandom_range(0, 511);
        write_addr = i;
        @(negedge clk);
        read_addr = i;
        c_pred=a+b;
        repeat(2)@(negedge clk);
        compare(dout, c_pred,read_addr);
    end

	#20
	$finish;
end

function void compare(reg[31:0] exp_addr, reg [31:0] cap_data,reg [8:0] read_addr);
if (cap_data !== exp_addr) begin
    $display("Status: Test Failed:: @%0t ADDR: %0d, Expected Data: %0h, Actual Data: %0h", $time, read_addr,exp_addr, cap_data); 
    // error++;
end
else begin
    $display("Status: Test Passed:: @%0t ADDR: %0d, Expected Data: %0h, Actual Data: %0h", $time, read_addr,exp_addr, cap_data); 
    // pass++;
end 
endfunction

endmodule

Testcases/ram_simple_dp_async_read_512x32/sim/rtl_sim/wave.vcd
$date
	Fri Aug  9 10:55:23 2024
$end
$version
	Icarus Verilog
$end
$timescale
	1ps
$end
$scope module testbench $end
$var wire 32 ! dout [31:0] $end
$var reg 32 " a [31:0] $end
$var reg 32 # b [31:0] $end
$var reg 32 $ c_pred [31:0] $end
$var reg 1 % clk $end
$var reg 1 & out_en $end
$var reg 9 ' read_addr [8:0] $end
$var reg 1 ( reset $end
$var reg 1 ) we $end
$var reg 9 * write_addr [8:0] $end
$upscope $end
$enddefinitions $end
$comment Show the parameter values. $end
$dumpall
$end
#0
$dumpvars
b0 *
0)
1(
b0 '
0&
0%
b0 $
b0 #
b0 "
bx !
$end
#1000
1%
#2000
0%
#3000
1%
#4000
0%
#5000
1%
#6000
0%
#7000
1%
#8000
0(
0%
#9000
b0 !
1%
#10000
0%
#11000
1%
#12000
0%
#13000
1%
#14000
0%
#15000
1%
#16000
0%
#17000
1%
#18000
1(
0%
#19000
bx !
1%
#20000
0%
#21000
1%
#22000
0%
#23000
1%
#24000
0%
#25000
1%
#26000
0%
#27000
1%
#28000
0%
#29000
1%
#30000
0%
#31000
1%
#32000
0%
#33000
1%
#34000
0%
#35000
1%
#36000
0%
#37000
1%
#38000
1&
1)
b10001000100010001000100010001 $
b10001000100010001000100010001 #
0%
#39000
b0 !
1%
#40000
0%
#41000
1%
#42000
0%
#43000
b10001000100010001000100010001 !
1%
#44000
0%
#45000
1%
#46000
0%
#47000
1%
#48000
0%
#49000
1%
#50000
0%
#51000
1%
#52000
0%
#53000
1%
#54000
0%
#55000
1%
#56000
0%
#57000
1%
#58000
0%
#59000
1%
#60000
0%
#61000
1%
#62000
0%
#63000
1%
#64000
0%
#65000
1%
#66000
0%
#67000
1%
#68000
b10000001 #
b100100100 "
0%
#69000
1%
#70000
b110100101 $
0%
#71000
1%
#72000
0%
#73000
b110100101 !
1%
#74000
b1 *
b1100011 #
b1001 "
0%
#75000
1%
#76000
b1101100 $
b1 '
0%
#77000
1%
#78000
0%
#79000
b1101100 !
1%
#80000
b10 *
b110001101 #
b100001101 "
0%
#81000
1%
#82000
b1010011010 $
b10 '
0%
#83000
1%
#84000
0%
#85000
b1010011010 !
1%
#86000
b11 *
b10010 #
b1100101 "
0%
#87000
1%
#88000
b1110111 $
b11 '
0%
#89000
1%
#90000
0%
#91000
b1110111 !
1%
#92000
b100 *
b100001101 #
b100000001 "
0%
#93000
1%
#94000
b1000001110 $
b100 '
0%
#95000
1%
#96000
0%
#97000
b1000001110 !
1%
#98000
b101 *
b100111101 #
b101110110 "
0%
#99000
1%
#100000
b1010110011 $
b101 '
0%
#101000
1%
#102000
0%
#103000
b1010110011 !
1%
#104000
b110 *
b110001100 #
b111101101 "
0%
#105000
1%
#106000
b1101111001 $
b110 '
0%
#107000
1%
#108000
0%
#109000
b1101111001 !
1%
#110000
b111 *
b11000110 #
b111111001 "
0%
#111000
1%
#112000
b1010111111 $
b111 '
0%
#113000
1%
#114000
0%
#115000
b1010111111 !
1%
#116000
b1000 *
b10101010 #
b11000101 "
0%
#117000
1%
#118000
b101101111 $
b1000 '
0%
#119000
1%
#120000
0%
#121000
b101101111 !
1%
#122000
b1001 *
b1110111 #
b111100101 "
0%
#123000
1%
#124000
b1001011100 $
b1001 '
0%
#125000
1%
#126000
0%
#127000
b1001011100 !
1%
#128000
b1010 *
b110001111 #
b10010 "
0%
#129000
1%
#130000
b110100001 $
b1010 '
0%
#131000
1%
#132000
0%
#133000
b110100001 !
1%
#134000
b1011 *
b11001110 #
b111110010 "
0%
#135000
1%
#136000
b1011000000 $
b1011 '
0%
#137000
1%
#138000
0%
#139000
b1011000000 !
1%
#140000
b1100 *
b11000101 #
b11101000 "
0%
#141000
1%
#142000
b110101101 $
b1100 '
0%
#143000
1%
#144000
0%
#145000
b110101101 !
1%
#146000
b1101 *
b10111101 #
b101011100 "
0%
#147000
1%
#148000
b1000011001 $
b1101 '
0%
#149000
1%
#150000
0%
#151000
b1000011001 !
1%
#152000
b1110 *
b1100101 #
b101101 "
0%
#153000
1%
#154000
b10010010 $
b1110 '
0%
#155000
1%
#156000
0%
#157000
b10010010 !
1%
#158000
b1111 *
b100001010 #
b1100011 "
0%
#159000
1%
#160000
b101101101 $
b1111 '
0%
#161000
1%
#162000
0%
#163000
b101101101 !
1%
#164000
b10000 *
b100100000 #
b10000000 "
0%
#165000
1%
#166000
b110100000 $
b10000 '
0%
#167000
1%
#168000
0%
#169000
b110100000 !
1%
#170000
b10001 *
b10011101 #
b110101010 "
0%
#171000
1%
#172000
b1001000111 $
b10001 '
0%
#173000
1%
#174000
0%
#175000
b1001000111 !
1%
#176000
b10010 *
b10011 #
b10010110 "
0%
#177000
1%
#178000
b10101001 $
b10010 '
0%
#179000
1%
#180000
0%
#181000
b10101001 !
1%
#182000
b10011 *
b1010011 #
b1101 "
0%
#183000
1%
#184000
b1100000 $
b10011 '
0%
#185000
1%
#186000
0%
#187000
b1100000 !
1%
#188000
b10100 *
b11010101 #
b101101011 "
0%
#189000
1%
#190000
b1001000000 $
b10100 '
0%
#191000
1%
#192000
0%
#193000
b1001000000 !
1%
#194000
b10101 *
b10101110 #
b10 "
0%
#195000
1%
#196000
b10110000 $
b10101 '
0%
#197000
1%
#198000
0%
#199000
b10110000 !
1%
#200000
b10110 *
b11001111 #
b100011101 "
0%
#201000
1%
#202000
b111101100 $
b10110 '
0%
#203000
1%
#204000
0%
#205000
b111101100 !
1%
#206000
b10111 *
b100001010 #
b100100011 "
0%
#207000
1%
#208000
b1000101101 $
b10111 '
0%
#209000
1%
#210000
0%
#211000
b1000101101 !
1%
#212000
b11000 *
b111100 #
b11001010 "
0%
#213000
1%
#214000
b100000110 $
b11000 '
0%
#215000
1%
#216000
0%
#217000
b100000110 !
1%
#218000
b11001 *
b110001010 #
b111110010 "
0%
#219000
1%
#220000
b1101111100 $
b11001 '
0%
#221000
1%
#222000
0%
#223000
b1101111100 !
1%
#224000
b11010 *
b11011000 #
b101000001 "
0%
#225000
1%
#226000
b1000011001 $
b11010 '
0%
#227000
1%
#228000
0%
#229000
b1000011001 !
1%
#230000
b11011 *
b10001001 #
b101111000 "
0%
#231000
1%
#232000
b1000000001 $
b11011 '
0%
#233000
1%
#234000
0%
#235000
b1000000001 !
1%
#236000
b11100 *
b110110110 #
b111101011 "
0%
#237000
1%
#238000
b1110100001 $
b11100 '
0%
#239000
1%
#240000
0%
#241000
b1110100001 !
1%
#242000
b11101 *
b110101110 #
b111000110 "
0%
#243000
1%
#244000
b1101110100 $
b11101 '
0%
#245000
1%
#246000
0%
#247000
b1101110100 !
1%
#248000
b11110 *
b100101010 #
b10111100 "
0%
#249000
1%
#250000
b111100110 $
b11110 '
0%
#251000
1%
#252000
0%
#253000
b111100110 !
1%
#254000
b11111 *
b1110001 #
b1011 "
0%
#255000
1%
#256000
b1111100 $
b11111 '
0%
#257000
1%
#258000
0%
#259000
b1111100 !
1%
#260000
b100000 *
b101001111 #
b110000101 "
0%
#261000
1%
#262000
b1011010100 $
b100000 '
0%
#263000
1%
#264000
0%
#265000
b1011010100 !
1%
#266000
b100001 *
b100111010 #
b111011 "
0%
#267000
1%
#268000
b101110101 $
b100001 '
0%
#269000
1%
#270000
0%
#271000
b101110101 !
1%
#272000
b100010 *
b100010101 #
b1111110 "
0%
#273000
1%
#274000
b110010011 $
b100010 '
0%
#275000
1%
#276000
0%
#277000
b110010011 !
1%
#278000
b100011 *
b111011001 #
b111110001 "
0%
#279000
1%
#280000
b1111001010 $
b100011 '
0%
#281000
1%
#282000
0%
#283000
b1111001010 !
1%
#284000
b100100 *
b101001100 #
b101100010 "
0%
#285000
1%
#286000
b1010101110 $
b100100 '
0%
#287000
1%
#288000
0%
#289000
b1010101110 !
1%
#290000
b100101 *
b110001111 #
b110011111 "
0%
#291000
1%
#292000
b1100101110 $
b100101 '
0%
#293000
1%
#294000
0%
#295000
b1100101110 !
1%
#296000
b100110 *
b10110111 #
b111111000 "
0%
#297000
1%
#298000
b1010101111 $
b100110 '
0%
#299000
1%
#300000
0%
#301000
b1010101111 !
1%
#302000
b100111 *
b1011100 #
b10011111 "
0%
#303000
1%
#304000
b11111011 $
b100111 '
0%
#305000
1%
#306000
0%
#307000
b11111011 !
1%
#308000
b101000 *
b110001001 #
b1011011 "
0%
#309000
1%
#310000
b111100100 $
b101000 '
0%
#311000
1%
#312000
0%
#313000
b111100100 !
1%
#314000
b101001 *
b11010000 #
b1001001 "
0%
#315000
1%
#316000
b100011001 $
b101001 '
0%
#317000
1%
#318000
0%
#319000
b100011001 !
1%
#320000
b101010 *
b1010001 #
b11010111 "
0%
#321000
1%
#322000
b100101000 $
b101010 '
0%
#323000
1%
#324000
0%
#325000
b100101000 !
1%
#326000
b101011 *
b100001100 #
b110010110 "
0%
#327000
1%
#328000
b1010100010 $
b101011 '
0%
#329000
1%
#330000
0%
#331000
b1010100010 !
1%
#332000
b101100 *
b111001000 #
b11000010 "
0%
#333000
1%
#334000
b1010001010 $
b101100 '
0%
#335000
1%
#336000
0%
#337000
b1010001010 !
1%
#338000
b101101 *
b100111101 #
b1110111 "
0%
#339000
1%
#340000
b110110100 $
b101101 '
0%
#341000
1%
#342000
0%
#343000
b110110100 !
1%
#344000
b101110 *
b1111110 #
b100010010 "
0%
#345000
1%
#346000
b110010000 $
b101110 '
0%
#347000
1%
#348000
0%
#349000
b110010000 !
1%
#350000
b101111 *
b100111001 #
b101101101 "
0%
#351000
1%
#352000
b1010100110 $
b101111 '
0%
#353000
1%
#354000
0%
#355000
b1010100110 !
1%
#356000
b110000 *
b11010011 #
b100011111 "
0%
#357000
1%
#358000
b111110010 $
b110000 '
0%
#359000
1%
#360000
0%
#361000
b111110010 !
1%
#362000
b110001 *
b1111000 #
b110000101 "
0%
#363000
1%
#364000
b111111101 $
b110001 '
0%
#365000
1%
#366000
0%
#367000
b111111101 !
1%
#368000
b110010 *
b101001001 #
b101011011 "
0%
#369000
1%
#370000
b1010100100 $
b110010 '
0%
#371000
1%
#372000
0%
#373000
b1010100100 !
1%
#374000
b110011 *
b100101010 #
b111111 "
0%
#375000
1%
#376000
b101101001 $
b110011 '
0%
#377000
1%
#378000
0%
#379000
b101101001 !
1%
#380000
b110100 *
b10000110 #
b101011000 "
0%
#381000
1%
#382000
b111011110 $
b110100 '
0%
#383000
1%
#384000
0%
#385000
b111011110 !
1%
#386000
b110101 *
b10011100 #
b10001110 "
0%
#387000
1%
#388000
b100101010 $
b110101 '
0%
#389000
1%
#390000
0%
#391000
b100101010 !
1%
#392000
b110110 *
b100110 #
b111111010 "
0%
#393000
1%
#394000
b1000100000 $
b110110 '
0%
#395000
1%
#396000
0%
#397000
b1000100000 !
1%
#398000
b110111 *
b10100011 #
b101110011 "
0%
#399000
1%
#400000
b1000010110 $
b110111 '
0%
#401000
1%
#402000
0%
#403000
b1000010110 !
1%
#404000
b111000 *
b10110011 #
b101111 "
0%
#405000
1%
#406000
b11100010 $
b111000 '
0%
#407000
1%
#408000
0%
#409000
b11100010 !
1%
#410000
b111001 *
b101000100 #
b1011111 "
0%
#411000
1%
#412000
b110100011 $
b111001 '
0%
#413000
1%
#414000
0%
#415000
b110100011 !
1%
#416000
b111010 *
b11001011 #
b111110111 "
0%
#417000
1%
#418000
b1011000010 $
b111010 '
0%
#419000
1%
#420000
0%
#421000
b1011000010 !
1%
#422000
b111011 *
b101011010 #
b11100110 "
0%
#423000
1%
#424000
b1001000000 $
b111011 '
0%
#425000
1%
#426000
0%
#427000
b1001000000 !
1%
#428000
b111100 *
b11101101 #
b100101001 "
0%
#429000
1%
#430000
b1000010110 $
b111100 '
0%
#431000
1%
#432000
0%
#433000
b1000010110 !
1%
#434000
b111101 *
b1100101 #
b11011010 "
0%
#435000
1%
#436000
b100111111 $
b111101 '
0%
#437000
1%
#438000
0%
#439000
b100111111 !
1%
#440000
b111110 *
b11011111 #
b10110101 "
0%
#441000
1%
#442000
b110010100 $
b111110 '
0%
#443000
1%
#444000
0%
#445000
b110010100 !
1%
#446000
b111111 *
b101000100 #
b101111001 "
0%
#447000
1%
#448000
b1010111101 $
b111111 '
0%
#449000
1%
#450000
0%
#451000
b1010111101 !
1%
#452000
b1000000 *
b100101010 #
b11010000 "
0%
#453000
1%
#454000
b111111010 $
b1000000 '
0%
#455000
1%
#456000
0%
#457000
b111111010 !
1%
#458000
b1000001 *
b100001110 #
b110101011 "
0%
#459000
1%
#460000
b1010111001 $
b1000001 '
0%
#461000
1%
#462000
0%
#463000
b1010111001 !
1%
#464000
b1000010 *
b10011010 #
b111011100 "
0%
#465000
1%
#466000
b1001110110 $
b1000010 '
0%
#467000
1%
#468000
0%
#469000
b1001110110 !
1%
#470000
b1000011 *
b11000011 #
b11111101 "
0%
#471000
1%
#472000
b111000000 $
b1000011 '
0%
#473000
1%
#474000
0%
#475000
b111000000 !
1%
#476000
b1000100 *
b101001110 #
b101010110 "
0%
#477000
1%
#478000
b1010100100 $
b1000100 '
0%
#479000
1%
#480000
0%
#481000
b1010100100 !
1%
#482000
b1000101 *
b1010 #
b1100111 "
0%
#483000
1%
#484000
b1110001 $
b1000101 '
0%
#485000
1%
#486000
0%
#487000
b1110001 !
1%
#488000
b1000110 *
b111000 #
b110110110 "
0%
#489000
1%
#490000
b111101110 $
b1000110 '
0%
#491000
1%
#492000
0%
#493000
b111101110 !
1%
#494000
b1000111 *
b10111000 #
b101111001 "
0%
#495000
1%
#496000
b1000110001 $
b1000111 '
0%
#497000
1%
#498000
0%
#499000
b1000110001 !
1%
#500000
b1001000 *
b110010011 #
b110010100 "
0%
#501000
1%
#502000
b1100100111 $
b1001000 '
0%
#503000
1%
#504000
0%
#505000
b1100100111 !
1%
#506000
b1001001 *
b1011001 #
b100 "
0%
#507000
1%
#508000
b1011101 $
b1001001 '
0%
#509000
1%
#510000
0%
#511000
b1011101 !
1%
#512000
b1001010 *
b1001101 #
b111011011 "
0%
#513000
1%
#514000
b1000101000 $
b1001010 '
0%
#515000
1%
#516000
0%
#517000
b1000101000 !
1%
#518000
b1001011 *
b1101101 #
b111011001 "
0%
#519000
1%
#520000
b1001000110 $
b1001011 '
0%
#521000
1%
#522000
0%
#523000
b1001000110 !
1%
#524000
b1001100 *
b111001010 #
b1110110 "
0%
#525000
1%
#526000
b1001000000 $
b1001100 '
0%
#527000
1%
#528000
0%
#529000
b1001000000 !
1%
#530000
b1001101 *
b110010101 #
b110110110 "
0%
#531000
1%
#532000
b1101001011 $
b1001101 '
0%
#533000
1%
#534000
0%
#535000
b1101001011 !
1%
#536000
b1001110 *
b100000100 #
b1000110 "
0%
#537000
1%
#538000
b101001010 $
b1001110 '
0%
#539000
1%
#540000
0%
#541000
b101001010 !
1%
#542000
b1001111 *
b101101001 #
b111110111 "
0%
#543000
1%
#544000
b1101100000 $
b1001111 '
0%
#545000
1%
#546000
0%
#547000
b1101100000 !
1%
#548000
b1010000 *
b110001000 #
b10110100 "
0%
#549000
1%
#550000
b1000111100 $
b1010000 '
0%
#551000
1%
#552000
0%
#553000
b1000111100 !
1%
#554000
b1010001 *
b101101 #
b100101000 "
0%
#555000
1%
#556000
b101010101 $
b1010001 '
0%
#557000
1%
#558000
0%
#559000
b101010101 !
1%
#560000
b1010010 *
b101110 #
b11000111 "
0%
#561000
1%
#562000
b11110101 $
b1010010 '
0%
#563000
1%
#564000
0%
#565000
b11110101 !
1%
#566000
b1010011 *
b100011100 #
b1000 "
0%
#567000
1%
#568000
b100100100 $
b1010011 '
0%
#569000
1%
#570000
0%
#571000
b100100100 !
1%
#572000
b1010100 *
b100101001 #
b11111101 "
0%
#573000
1%
#574000
b1000100110 $
b1010100 '
0%
#575000
1%
#576000
0%
#577000
b1000100110 !
1%
#578000
b1010101 *
b110000110 #
b11100 "
0%
#579000
1%
#580000
b110100010 $
b1010101 '
0%
#581000
1%
#582000
0%
#583000
b110100010 !
1%
#584000
b1010110 *
b111101 #
b11011010 "
0%
#585000
1%
#586000
b100010111 $
b1010110 '
0%
#587000
1%
#588000
0%
#589000
b100010111 !
1%
#590000
b1010111 *
b1110000 #
b101100110 "
0%
#591000
1%
#592000
b111010110 $
b1010111 '
0%
#593000
1%
#594000
0%
#595000
b111010110 !
1%
#596000
b1011000 *
b110111010 #
b1110011 "
0%
#597000
1%
#598000
b1000101101 $
b1011000 '
0%
#599000
1%
#600000
0%
#601000
b1000101101 !
1%
#602000
b1011001 *
b111111010 #
b101011110 "
0%
#603000
1%
#604000
b1101011000 $
b1011001 '
0%
#605000
1%
#606000
0%
#607000
b1101011000 !
1%
#608000
b1011010 *
b11010 #
b111010101 "
0%
#609000
1%
#610000
b111101111 $
b1011010 '
0%
#611000
1%
#612000
0%
#613000
b111101111 !
1%
#614000
b1011011 *
b100110111 #
b10111001 "
0%
#615000
1%
#616000
b111110000 $
b1011011 '
0%
#617000
1%
#618000
0%
#619000
b111110000 !
1%
#620000
b1011100 *
b111000000 #
b110010110 "
0%
#621000
1%
#622000
b1101010110 $
b1011100 '
0%
#623000
1%
#624000
0%
#625000
b1101010110 !
1%
#626000
b1011101 *
b10110110 #
b100100110 "
0%
#627000
1%
#628000
b111011100 $
b1011101 '
0%
#629000
1%
#630000
0%
#631000
b111011100 !
1%
#632000
b1011110 *
b111011100 #
b101111101 "
0%
#633000
1%
#634000
b1101011001 $
b1011110 '
0%
#635000
1%
#636000
0%
#637000
b1101011001 !
1%
#638000
b1011111 *
b101111000 #
b110000110 "
0%
#639000
1%
#640000
b1011111110 $
b1011111 '
0%
#641000
1%
#642000
0%
#643000
b1011111110 !
1%
#644000
b1100000 *
b11011011 #
b101111110 "
0%
#645000
1%
#646000
b1001011001 $
b1100000 '
0%
#647000
1%
#648000
0%
#649000
b1001011001 !
1%
#650000
b1100001 *
b101111001 #
b11001111 "
0%
#651000
1%
#652000
b1001001000 $
b1100001 '
0%
#653000
1%
#654000
0%
#655000
b1001001000 !
1%
#656000
b1100010 *
b1100001 #
b11111010 "
0%
#657000
1%
#658000
b101011011 $
b1100010 '
0%
#659000
1%
#660000
0%
#661000
b101011011 !
1%
#662000
b1100011 *
b10100001 #
b100010111 "
0%
#663000
1%
#664000
b110111000 $
b1100011 '
0%
#665000
1%
#666000
0%
#667000
b110111000 !
1%
#668000
b1100100 *
b1010000 #
b110000110 "
0%
#669000
1%
#670000
b111010110 $
b1100100 '
0%
#671000
1%
#672000
0%
#673000
b111010110 !
1%
#674000
b1100101 *
b110101 #
b111110101 "
0%
#675000
1%
#676000
b1000101010 $
b1100101 '
0%
#677000
1%
#678000
0%
#679000
b1000101010 !
1%
#680000
b1100110 *
b111000001 #
b101001 "
0%
#681000
1%
#682000
b111101010 $
b1100110 '
0%
#683000
1%
#684000
0%
#685000
b111101010 !
1%
#686000
b1100111 *
b10011000 #
b11000101 "
0%
#687000
1%
#688000
b101011101 $
b1100111 '
0%
#689000
1%
#690000
0%
#691000
b101011101 !
1%
#692000
b1101000 *
b1110011 #
b101001011 "
0%
#693000
1%
#694000
b110111110 $
b1101000 '
0%
#695000
1%
#696000
0%
#697000
b110111110 !
1%
#698000
b1101001 *
b10001010 #
b11101100 "
0%
#699000
1%
#700000
b101110110 $
b1101001 '
0%
#701000
1%
#702000
0%
#703000
b101110110 !
1%
#704000
b1101010 *
b10101000 #
b101001110 "
0%
#705000
1%
#706000
b111110110 $
b1101010 '
0%
#707000
1%
#708000
0%
#709000
b111110110 !
1%
#710000
b1101011 *
b10100001 #
b110101001 "
0%
#711000
1%
#712000
b1001001010 $
b1101011 '
0%
#713000
1%
#714000
0%
#715000
b1001001010 !
1%
#716000
b1101100 *
b11100110 #
b100001110 "
0%
#717000
1%
#718000
b111110100 $
b1101100 '
0%
#719000
1%
#720000
0%
#721000
b111110100 !
1%
#722000
b1101101 *
b100101010 #
b10011111 "
0%
#723000
1%
#724000
b111001001 $
b1101101 '
0%
#725000
1%
#726000
0%
#727000
b111001001 !
1%
#728000
b1101110 *
b10001101 #
b100101010 "
0%
#729000
1%
#730000
b110110111 $
b1101110 '
0%
#731000
1%
#732000
0%
#733000
b110110111 !
1%
#734000
b1101111 *
b111000 #
b110011110 "
0%
#735000
1%
#736000
b111010110 $
b1101111 '
0%
#737000
1%
#738000
0%
#739000
b111010110 !
1%
#740000
b1110000 *
b111001000 #
b1111001 "
0%
#741000
1%
#742000
b1001000001 $
b1110000 '
0%
#743000
1%
#744000
0%
#745000
b1001000001 !
1%
#746000
b1110001 *
b100010011 #
b111001010 "
0%
#747000
1%
#748000
b1011011101 $
b1110001 '
0%
#749000
1%
#750000
0%
#751000
b1011011101 !
1%
#752000
b1110010 *
b11000111 #
b101101011 "
0%
#753000
1%
#754000
b1000110010 $
b1110010 '
0%
#755000
1%
#756000
0%
#757000
b1000110010 !
1%
#758000
b1110011 *
b110111010 #
b110110110 "
0%
#759000
1%
#760000
b1101110000 $
b1110011 '
0%
#761000
1%
#762000
0%
#763000
b1101110000 !
1%
#764000
b1110100 *
b110111001 #
b111000100 "
0%
#765000
1%
#766000
b1101111101 $
b1110100 '
0%
#767000
1%
#768000
0%
#769000
b1101111101 !
1%
#770000
b1110101 *
b10110100 #
b110010010 "
0%
#771000
1%
#772000
b1001000110 $
b1110101 '
0%
#773000
1%
#774000
0%
#775000
b1001000110 !
1%
#776000
b1110110 *
b10000110 #
b101111111 "
0%
#777000
1%
#778000
b1000000101 $
b1110110 '
0%
#779000
1%
#780000
0%
#781000
b1000000101 !
1%
#782000
b1110111 *
b11110010 #
b111111010 "
0%
#783000
1%
#784000
b1011101100 $
b1110111 '
0%
#785000
1%
#786000
0%
#787000
b1011101100 !
1%
#788000
b1111000 *
b10111101 #
b100110010 "
0%
#789000
1%
#790000
b111101111 $
b1111000 '
0%
#791000
1%
#792000
0%
#793000
b111101111 !
1%
#794000
b1111001 *
b11100100 #
b110000100 "
0%
#795000
1%
#796000
b1001101000 $
b1111001 '
0%
#797000
1%
#798000
0%
#799000
b1001101000 !
1%
#800000
b1111010 *
b110101001 #
b111001010 "
0%
#801000
1%
#802000
b1101110011 $
b1111010 '
0%
#803000
1%
#804000
0%
#805000
b1101110011 !
1%
#806000
b1111011 *
b110001110 #
b10100001 "
0%
#807000
1%
#808000
b1000101111 $
b1111011 '
0%
#809000
1%
#810000
0%
#811000
b1000101111 !
1%
#812000
b1111100 *
b1011 #
b11111011 "
0%
#813000
1%
#814000
b100000110 $
b1111100 '
0%
#815000
1%
#816000
0%
#817000
b100000110 !
1%
#818000
b1111101 *
b111001001 #
b11101111 "
0%
#819000
1%
#820000
b1010111000 $
b1111101 '
0%
#821000
1%
#822000
0%
#823000
b1010111000 !
1%
#824000
b1111110 *
b1110101 #
b100110110 "
0%
#825000
1%
#826000
b110101011 $
b1111110 '
0%
#827000
1%
#828000
0%
#829000
b110101011 !
1%
#830000
b1111111 *
b101101011 #
b10001111 "
0%
#831000
1%
#832000
b111111010 $
b1111111 '
0%
#833000
1%
#834000
0%
#835000
b111111010 !
1%
#836000
b10000000 *
b10101110 #
b110001000 "
0%
#837000
1%
#838000
b1000110110 $
b10000000 '
0%
#839000
1%
#840000
0%
#841000
b1000110110 !
1%
#842000
b10000001 *
b110010010 #
b110011011 "
0%
#843000
1%
#844000
b1100101101 $
b10000001 '
0%
#845000
1%
#846000
0%
#847000
b1100101101 !
1%
#848000
b10000010 *
b101101 #
b100101000 "
0%
#849000
1%
#850000
b101010101 $
b10000010 '
0%
#851000
1%
#852000
0%
#853000
b101010101 !
1%
#854000
b10000011 *
b11000010 #
b101001011 "
0%
#855000
1%
#856000
b1000001101 $
b10000011 '
0%
#857000
1%
#858000
0%
#859000
b1000001101 !
1%
#860000
b10000100 *
b100001101 #
b11110 "
0%
#861000
1%
#862000
b100101011 $
b10000100 '
0%
#863000
1%
#864000
0%
#865000
b100101011 !
1%
#866000
b10000101 *
b100011000 #
b111101100 "
0%
#867000
1%
#868000
b1100000100 $
b10000101 '
0%
#869000
1%
#870000
0%
#871000
b1100000100 !
1%
#872000
b10000110 *
b10000110 #
b111010001 "
0%
#873000
1%
#874000
b1001010111 $
b10000110 '
0%
#875000
1%
#876000
0%
#877000
b1001010111 !
1%
#878000
b10000111 *
b111011 #
b1000001 "
0%
#879000
1%
#880000
b1111100 $
b10000111 '
0%
#881000
1%
#882000
0%
#883000
b1111100 !
1%
#884000
b10001000 *
b101010011 #
b111011000 "
0%
#885000
1%
#886000
b1100101011 $
b10001000 '
0%
#887000
1%
#888000
0%
#889000
b1100101011 !
1%
#890000
b10001001 *
b1011011 #
b1010110 "
0%
#891000
1%
#892000
b10110001 $
b10001001 '
0%
#893000
1%
#894000
0%
#895000
b10110001 !
1%
#896000
b10001010 *
b100 #
b11100010 "
0%
#897000
1%
#898000
b11100110 $
b10001010 '
0%
#899000
1%
#900000
0%
#901000
b11100110 !
1%
#902000
b10001011 *
b11011000 #
b101110011 "
0%
#903000
1%
#904000
b1001001011 $
b10001011 '
0%
#905000
1%
#906000
0%
#907000
b1001001011 !
1%
#908000
b10001100 *
b10111000 #
b100010010 "
0%
#909000
1%
#910000
b111001010 $
b10001100 '
0%
#911000
1%
#912000
0%
#913000
b111001010 !
1%
#914000
b10001101 *
b11100101 #
b111001 "
0%
#915000
1%
#916000
b100011110 $
b10001101 '
0%
#917000
1%
#918000
0%
#919000
b100011110 !
1%
#920000
b10001110 *
b100101011 #
b10100001 "
0%
#921000
1%
#922000
b111001100 $
b10001110 '
0%
#923000
1%
#924000
0%
#925000
b111001100 !
1%
#926000
b10001111 *
b111001000 #
b110000001 "
0%
#927000
1%
#928000
b1101001001 $
b10001111 '
0%
#929000
1%
#930000
0%
#931000
b1101001001 !
1%
#932000
b10010000 *
b110100001 #
b100100111 "
0%
#933000
1%
#934000
b1011001000 $
b10010000 '
0%
#935000
1%
#936000
0%
#937000
b1011001000 !
1%
#938000
b10010001 *
b100 #
b11111 "
0%
#939000
1%
#940000
b100011 $
b10010001 '
0%
#941000
1%
#942000
0%
#943000
b100011 !
1%
