Testcases/rom/sim/basic_tb/rom.v
module rom (
input clk, 
input [6:0] address,
output reg [7:0] data
);

reg [7:0] mem [127:0];

initial $readmemb("memory_file.mem", mem); 

always @(posedge clk) begin
   data <= mem[address];
end 

endmodule

Testcases/rom/sim/basic_tb/basic_tb.v
`include "rom.v"

module rom_post_route_tb;
  bit clk;
  bit [6:0] address;
  wire [7:0] data;

  integer i=0;
  
  rom golden (.*);

  always
  #1  clk = !clk;
  
  initial begin
    for (i = 0; i <128; i = i +1 )begin
        @(negedge clk); 
        address = i;
        $display("Data Mismatch. Address: %0d, data: %0d, Time: %0t", data, address, $time);
      end
      
    $finish;
  end
  
  initial begin
    $dumpfile("rom_formal.vcd");
    $dumpvars(1, rom_post_route_tb);
end

endmodule

Testcases/rom/sim/basic_tb/rom_formal.vcd
$date
	Tue Mar 14 17:16:09 2023
$end

$version
	Synopsys VCS version S-2021.09-SP2_Full64
$end

$timescale
	1s
$end

$comment Csum: 1 bb6171eb381bb96a $end


$scope module rom_post_route_tb $end
$var reg 1 ! clk $end
$var reg 8 " address [7:0] $end
$var wire 8 # data [7:0] $end
$var integer 32 $ i $end
$upscope $end

$enddefinitions $end

#0
$dumpvars
0!
bxxxxxxxx #
b00000000000000000000000000000000 $
b00000000 "
$end
#1
1!
b00000000 #
#2
0!
b00000000000000000000000000000001 $
#3
1!
#4
0!
b00000001 "
b00000000000000000000000000000010 $
#5
1!
b00000001 #
#6
0!
b00000010 "
b00000000000000000000000000000011 $
#7
1!
b00000010 #
#8
0!
b00000011 "
b00000000000000000000000000000100 $
#9
1!
b00000011 #
#10
0!
b00000100 "
b00000000000000000000000000000101 $
#11
1!
b11111100 #
#12
0!
b00000101 "
b00000000000000000000000000000110 $
#13
1!
b11111101 #
#14
0!
b00000110 "
b00000000000000000000000000000111 $
#15
1!
b11111110 #
#16
0!
b00000111 "
b00000000000000000000000000001000 $
#17
1!
b11111111 #
#18
0!
b00001000 "
b00000000000000000000000000001001 $
#19
1!
b00000000 #
#20
0!
b00001001 "
b00000000000000000000000000001010 $
#21
1!
b00000001 #
#22
0!
b00001010 "
b00000000000000000000000000001011 $
#23
1!
b00000010 #
#24
0!
b00001011 "
b00000000000000000000000000001100 $
#25
1!
b00000011 #
#26
0!
b00001100 "
b00000000000000000000000000001101 $
#27
1!
b11111100 #
#28
0!
b00001101 "
b00000000000000000000000000001110 $
#29
1!
b11111101 #
#30
0!
b00001110 "
b00000000000000000000000000001111 $
#31
1!
b11111110 #
#32
0!
b00001111 "
b00000000000000000000000000010000 $
#33
1!
b11111111 #
#34
0!
b00010000 "
b00000000000000000000000000010001 $
#35
1!
b00000000 #
#36
0!
b00010001 "
b00000000000000000000000000010010 $
#37
1!
b00000001 #
#38
0!
b00010010 "
b00000000000000000000000000010011 $
#39
1!
b00000010 #
#40
0!
b00010011 "
b00000000000000000000000000010100 $
#41
1!
b00000011 #
#42
0!
b00010100 "
b00000000000000000000000000010101 $
#43
1!
b11111100 #
#44
0!
b00010101 "
b00000000000000000000000000010110 $
#45
1!
b11111101 #
#46
0!
b00010110 "
b00000000000000000000000000010111 $
#47
1!
b11111110 #
#48
0!
b00010111 "
b00000000000000000000000000011000 $
#49
1!
b11111111 #
#50
0!
b00011000 "
b00000000000000000000000000011001 $
#51
1!
b00000000 #
#52
0!
b00011001 "
b00000000000000000000000000011010 $
#53
1!
b00000001 #
#54
0!
b00011010 "
b00000000000000000000000000011011 $
#55
1!
b00000010 #
#56
0!
b00011011 "
b00000000000000000000000000011100 $
#57
1!
b00000011 #
#58
0!
b00011100 "
b00000000000000000000000000011101 $
#59
1!
b11111100 #
#60
0!
b00011101 "
b00000000000000000000000000011110 $
#61
1!
b11111101 #
#62
0!
b00011110 "
b00000000000000000000000000011111 $
#63
1!
b11111110 #
#64
0!
b00011111 "
b00000000000000000000000000100000 $
#65
1!
b11111111 #
#66
0!
b00100000 "
b00000000000000000000000000100001 $
#67
1!
b00000000 #
#68
0!
b00100001 "
b00000000000000000000000000100010 $
#69
1!
b00000001 #
#70
0!
b00100010 "
b00000000000000000000000000100011 $
#71
1!
b00000010 #
#72
0!
b00100011 "
b00000000000000000000000000100100 $
#73
1!
b00000011 #
#74
0!
b00100100 "
b00000000000000000000000000100101 $
#75
1!
b11111100 #
#76
0!
b00100101 "
b00000000000000000000000000100110 $
#77
1!
b11111101 #
#78
0!
b00100110 "
b00000000000000000000000000100111 $
#79
1!
b11111110 #
#80
0!
b00100111 "
b00000000000000000000000000101000 $
#81
1!
b11111111 #
#82
0!
b00101000 "
b00000000000000000000000000101001 $
#83
1!
b00000000 #
#84
0!
b00101001 "
b00000000000000000000000000101010 $
#85
1!
b00000001 #
#86
0!
b00101010 "
b00000000000000000000000000101011 $
#87
1!
b00000010 #
#88
0!
b00101011 "
b00000000000000000000000000101100 $
#89
1!
b00000011 #
#90
0!
b00101100 "
b00000000000000000000000000101101 $
#91
1!
b11111100 #
#92
0!
b00101101 "
b00000000000000000000000000101110 $
#93
1!
b11111101 #
#94
0!
b00101110 "
b00000000000000000000000000101111 $
#95
1!
b11111110 #
#96
0!
b00101111 "
b00000000000000000000000000110000 $
#97
1!
b11111111 #
#98
0!
b00110000 "
b00000000000000000000000000110001 $
#99
1!
b00000000 #
#100
0!
b00110001 "
b00000000000000000000000000110010 $
#101
1!
b00000001 #
#102
0!
b00110010 "
b00000000000000000000000000110011 $
#103
1!
b00000010 #
#104
0!
b00110011 "
b00000000000000000000000000110100 $
#105
1!
b00000011 #
#106
0!
b00110100 "
b00000000000000000000000000110101 $
#107
1!
b11111100 #
#108
0!
b00110101 "
b00000000000000000000000000110110 $
#109
1!
b11111101 #
#110
0!
b00110110 "
b00000000000000000000000000110111 $
#111
1!
b11111110 #
#112
0!
b00110111 "
b00000000000000000000000000111000 $
#113
1!
b11111111 #
#114
0!
b00111000 "
b00000000000000000000000000111001 $
#115
1!
b00000000 #
#116
0!
b00111001 "
b00000000000000000000000000111010 $
#117
1!
b00000001 #
#118
0!
b00111010 "
b00000000000000000000000000111011 $
#119
1!
b00000010 #
#120
0!
b00111011 "
b00000000000000000000000000111100 $
#121
1!
b00000011 #
#122
0!
b00111100 "
b00000000000000000000000000111101 $
#123
1!
b11111100 #
#124
0!
b00111101 "
b00000000000000000000000000111110 $
#125
1!
b11111101 #
#126
0!
b00111110 "
b00000000000000000000000000111111 $
#127
1!
b11111110 #
#128
0!
b00111111 "
b00000000000000000000000001000000 $
#129
1!
b11111111 #
#130
0!
b01000000 "
b00000000000000000000000001000001 $
#131
1!
b00000000 #
#132
0!
b01000001 "
b00000000000000000000000001000010 $
#133
1!
b00000001 #
#134
0!
b01000010 "
b00000000000000000000000001000011 $
#135
1!
b00000010 #
#136
0!
b01000011 "
b00000000000000000000000001000100 $
#137
1!
b00000011 #
#138
0!
b01000100 "
b00000000000000000000000001000101 $
#139
1!
b11111100 #
#140
0!
b01000101 "
b00000000000000000000000001000110 $
#141
1!
b11111101 #
#142
0!
b01000110 "
b00000000000000000000000001000111 $
#143
1!
b11111110 #
#144
0!
b01000111 "
b00000000000000000000000001001000 $
#145
1!
b11111111 #
#146
0!
b01001000 "
b00000000000000000000000001001001 $
#147
1!
b00000000 #
#148
0!
b01001001 "
b00000000000000000000000001001010 $
#149
1!
b00000001 #
#150
0!
b01001010 "
b00000000000000000000000001001011 $
#151
1!
b00000010 #
#152
0!
b01001011 "
b00000000000000000000000001001100 $
#153
1!
b00000011 #
#154
0!
b01001100 "
b00000000000000000000000001001101 $
#155
1!
b11111100 #
#156
0!
b01001101 "
b00000000000000000000000001001110 $
#157
1!
b11111101 #
#158
0!
b01001110 "
b00000000000000000000000001001111 $
#159
1!
b11111110 #
#160
0!
b01001111 "
b00000000000000000000000001010000 $
#161
1!
b11111111 #
#162
0!
b01010000 "
b00000000000000000000000001010001 $
#163
1!
b00000000 #
#164
0!
b01010001 "
b00000000000000000000000001010010 $
#165
1!
b00000001 #
#166
0!
b01010010 "
b00000000000000000000000001010011 $
#167
1!
b00000010 #
#168
0!
b01010011 "
b00000000000000000000000001010100 $
#169
1!
b00000011 #
#170
0!
b01010100 "
b00000000000000000000000001010101 $
#171
1!
b11111100 #
#172
0!
b01010101 "
b00000000000000000000000001010110 $
#173
1!
b11111101 #
#174
0!
b01010110 "
b00000000000000000000000001010111 $
#175
1!
b11111110 #
#176
0!
b01010111 "
b00000000000000000000000001011000 $
#177
1!
b11111111 #
#178
0!
b01011000 "
b00000000000000000000000001011001 $
#179
1!
b00000000 #
#180
0!
b01011001 "
b00000000000000000000000001011010 $
#181
1!
b00000001 #
#182
0!
b01011010 "
b00000000000000000000000001011011 $
#183
1!
b00000010 #
#184
0!
b01011011 "
b00000000000000000000000001011100 $
#185
1!
b00000011 #
#186
0!
b01011100 "
b00000000000000000000000001011101 $
#187
1!
b11111100 #
#188
0!
b01011101 "
b00000000000000000000000001011110 $
#189
1!
b11111101 #
#190
0!
b01011110 "
b00000000000000000000000001011111 $
#191
1!
b11111110 #
#192
0!
b01011111 "
b00000000000000000000000001100000 $
#193
1!
b11111111 #
#194
0!
b01100000 "
b00000000000000000000000001100001 $
#195
1!
b00000000 #
#196
0!
b01100001 "
b00000000000000000000000001100010 $
#197
1!
b00000001 #
#198
0!
b01100010 "
b00000000000000000000000001100011 $
#199
1!
b00000010 #
#200
0!
b01100011 "
b00000000000000000000000001100100 $
#201
1!
b00000011 #
#202
0!
b01100100 "
b00000000000000000000000001100101 $
#203
1!
b11111100 #
#204
0!
b01100101 "
b00000000000000000000000001100110 $
#205
1!
b11111101 #
#206
0!
b01100110 "
b00000000000000000000000001100111 $
#207
1!
b11111110 #
#208
0!
b01100111 "
b00000000000000000000000001101000 $
#209
1!
b11111111 #
#210
0!
b01101000 "
b00000000000000000000000001101001 $
#211
1!
b00000000 #
#212
0!
b01101001 "
b00000000000000000000000001101010 $
#213
1!
b00000001 #
#214
0!
b01101010 "
b00000000000000000000000001101011 $
#215
1!
b00000010 #
#216
0!
b01101011 "
b00000000000000000000000001101100 $
#217
1!
b00000011 #
#218
0!
b01101100 "
b00000000000000000000000001101101 $
#219
1!
b11111100 #
#220
0!
b01101101 "
b00000000000000000000000001101110 $
#221
1!
b11111101 #
#222
0!
b01101110 "
b00000000000000000000000001101111 $
#223
1!
b11111110 #
#224
0!
b01101111 "
b00000000000000000000000001110000 $
#225
1!
b11111111 #
#226
0!
b01110000 "
b00000000000000000000000001110001 $
#227
1!
b00000000 #
#228
0!
b01110001 "
b00000000000000000000000001110010 $
#229
1!
b00000001 #
#230
0!
b01110010 "
b00000000000000000000000001110011 $
#231
1!
b00000010 #
#232
0!
b01110011 "
b00000000000000000000000001110100 $
#233
1!
b00000011 #
#234
0!
b01110100 "
b00000000000000000000000001110101 $
#235
1!
b11111100 #
#236
0!
b01110101 "
b00000000000000000000000001110110 $
#237
1!
b11111101 #
#238
0!
b01110110 "
b00000000000000000000000001110111 $
#239
1!
b11111110 #
#240
0!
b01110111 "
b00000000000000000000000001111000 $
#241
1!
b11111111 #
#242
0!
b01111000 "
b00000000000000000000000001111001 $
#243
1!
b00000000 #
#244
0!
b01111001 "
b00000000000000000000000001111010 $
#245
1!
b00000001 #
#246
0!
b01111010 "
b00000000000000000000000001111011 $
#247
1!
b00000010 #
#248
0!
b01111011 "
b00000000000000000000000001111100 $
#249
1!
b00000011 #
#250
0!
b01111100 "
b00000000000000000000000001111101 $
#251
1!
b11111100 #
#252
0!
b01111101 "
b00000000000000000000000001111110 $
#253
1!
b11111101 #
#254
0!
b01111110 "
b00000000000000000000000001111111 $
#255
1!
b11111110 #
#256
0!
b01111111 "
b00000000000000000000000010000000 $
#257
1!
b11111111 #
#258
0!
b10000000 "
b00000000000000000000000010000001 $
#259
1!
b00000000 #
#260
0!
b10000001 "
b00000000000000000000000010000010 $
#261
1!
b00000001 #
#262
0!
b10000010 "
b00000000000000000000000010000011 $
#263
1!
b00000010 #
#264
0!
b10000011 "
b00000000000000000000000010000100 $
#265
1!
b00000011 #
#266
0!
b10000100 "
b00000000000000000000000010000101 $
#267
1!
b11111100 #
#268
0!
b10000101 "
b00000000000000000000000010000110 $
#269
1!
b11111101 #
#270
0!
b10000110 "
b00000000000000000000000010000111 $
#271
1!
b11111110 #
#272
0!
b10000111 "
b00000000000000000000000010001000 $
#273
1!
b11111111 #
#274
0!
b10001000 "
b00000000000000000000000010001001 $
#275
1!
b00000000 #
#276
0!
b10001001 "
b00000000000000000000000010001010 $
#277
1!
b00000001 #
#278
0!
b10001010 "
b00000000000000000000000010001011 $
#279
1!
b00000010 #
#280
0!
b10001011 "
b00000000000000000000000010001100 $
#281
1!
b00000011 #
#282
0!
b10001100 "
b00000000000000000000000010001101 $
#283
1!
b11111100 #
#284
0!
b10001101 "
b00000000000000000000000010001110 $
#285
1!
b11111101 #
#286
0!
b10001110 "
b00000000000000000000000010001111 $
#287
1!
b11111110 #
#288
0!
b10001111 "
b00000000000000000000000010010000 $
#289
1!
b11111111 #
#290
0!
b10010000 "
b00000000000000000000000010010001 $
#291
1!
b00000000 #
#292
0!
b10010001 "
b00000000000000000000000010010010 $
#293
1!
b00000001 #
#294
0!
b10010010 "
b00000000000000000000000010010011 $
#295
1!
b00000010 #
#296
0!
b10010011 "
b00000000000000000000000010010100 $
#297
1!
b00000011 #
#298
0!
b10010100 "
b00000000000000000000000010010101 $
#299
1!
b11111100 #
#300
0!
b10010101 "
b00000000000000000000000010010110 $
#301
1!
b11111101 #
#302
0!
b10010110 "
b00000000000000000000000010010111 $
#303
1!
b11111110 #
#304
0!
b10010111 "
b00000000000000000000000010011000 $
#305
1!
b11111111 #
#306
0!
b10011000 "
b00000000000000000000000010011001 $
#307
1!
b00000000 #
#308
0!
b10011001 "
b00000000000000000000000010011010 $
#309
1!
b00000001 #
#310
0!
b10011010 "
b00000000000000000000000010011011 $
#311
1!
b00000010 #
#312
0!
b10011011 "
b00000000000000000000000010011100 $
#313
1!
b00000011 #
#314
0!
b10011100 "
b00000000000000000000000010011101 $
#315
1!
b11111100 #
#316
0!
b10011101 "
b00000000000000000000000010011110 $
#317
1!
b11111101 #
#318
0!
b10011110 "
b00000000000000000000000010011111 $
#319
1!
b11111110 #
#320
0!
b10011111 "
b00000000000000000000000010100000 $
#321
1!
b11111111 #
#322
0!
b10100000 "
b00000000000000000000000010100001 $
#323
1!
b00000000 #
#324
0!
b10100001 "
b00000000000000000000000010100010 $
#325
1!
b00000001 #
#326
0!
b10100010 "
b00000000000000000000000010100011 $
#327
1!
b00000010 #
#328
0!
b10100011 "
b00000000000000000000000010100100 $
#329
1!
b00000011 #
#330
0!
b10100100 "
b00000000000000000000000010100101 $
#331
1!
b11111100 #
#332
0!
b10100101 "
b00000000000000000000000010100110 $
#333
1!
b11111101 #
#334
0!
b10100110 "
b00000000000000000000000010100111 $
#335
1!
b11111110 #
#336
0!
b10100111 "
b00000000000000000000000010101000 $
#337
1!
b11111111 #
#338
0!
b10101000 "
b00000000000000000000000010101001 $
#339
1!
b00000000 #
#340
0!
b10101001 "
b00000000000000000000000010101010 $
#341
1!
b00000001 #
#342
0!
b10101010 "
b00000000000000000000000010101011 $
#343
1!
b00000010 #
#344
0!
b10101011 "
b00000000000000000000000010101100 $
#345
1!
b00000011 #
#346
0!
b10101100 "
b00000000000000000000000010101101 $
#347
1!
b11111100 #
#348
0!
b10101101 "
b00000000000000000000000010101110 $
#349
1!
b11111101 #
#350
0!
b10101110 "
b00000000000000000000000010101111 $
#351
1!
b11111110 #
#352
0!
b10101111 "
b00000000000000000000000010110000 $
#353
1!
b11111111 #
#354
0!
b10110000 "
b00000000000000000000000010110001 $
#355
1!
b00000000 #
#356
0!
b10110001 "
b00000000000000000000000010110010 $
#357
1!
b00000001 #
#358
0!
b10110010 "
b00000000000000000000000010110011 $
#359
1!
b00000010 #
#360
0!
b10110011 "
b00000000000000000000000010110100 $
#361
1!
b00000011 #
#362
0!
b10110100 "
b00000000000000000000000010110101 $
#363
1!
b11111100 #
#364
0!
b10110101 "
b00000000000000000000000010110110 $
#365
1!
b11111101 #
#366
0!
b10110110 "
b00000000000000000000000010110111 $
#367
1!
b11111110 #
#368
0!
b10110111 "
b00000000000000000000000010111000 $
#369
1!
b11111111 #
#370
0!
b10111000 "
b00000000000000000000000010111001 $
#371
1!
b00000000 #
#372
0!
b10111001 "
b00000000000000000000000010111010 $
#373
1!
b00000001 #
#374
0!
b10111010 "
b00000000000000000000000010111011 $
#375
1!
b00000010 #
#376
0!
b10111011 "
b00000000000000000000000010111100 $
#377
1!
b00000011 #
#378
0!
b10111100 "
b00000000000000000000000010111101 $
#379
1!
b11111100 #
#380
0!
b10111101 "
b00000000000000000000000010111110 $
#381
1!
b11111101 #
#382
0!
b10111110 "
b00000000000000000000000010111111 $
#383
1!
b11111110 #
#384
0!
b10111111 "
b00000000000000000000000011000000 $
#385
1!
b11111111 #
#386
0!
b11000000 "
b00000000000000000000000011000001 $
#387
1!
b00000000 #
#388
0!
b11000001 "
b00000000000000000000000011000010 $
#389
1!
b00000001 #
#390
0!
b11000010 "
b00000000000000000000000011000011 $
#391
1!
b00000010 #
#392
0!
b11000011 "
b00000000000000000000000011000100 $
#393
1!
b00000011 #
#394
0!
b11000100 "
b00000000000000000000000011000101 $
#395
1!
b11111100 #
#396
0!
b11000101 "
b00000000000000000000000011000110 $
#397
1!
b11111101 #
#398
0!
b11000110 "
b00000000000000000000000011000111 $
#399
1!
b11111110 #
#400
0!
b11000111 "
b00000000000000000000000011001000 $
#401
1!
b11111111 #
#402
0!
b11001000 "
b00000000000000000000000011001001 $
#403
1!
b00000000 #
#404
0!
b11001001 "
b00000000000000000000000011001010 $
#405
1!
b00000001 #
#406
0!
b11001010 "
b00000000000000000000000011001011 $
#407
1!
b00000010 #
#408
0!
b11001011 "
b00000000000000000000000011001100 $
#409
1!
b00000011 #
#410
0!
b11001100 "
b00000000000000000000000011001101 $
#411
1!
b11111100 #
#412
0!
b11001101 "
b00000000000000000000000011001110 $
#413
1!
b11111101 #
#414
0!
b11001110 "
b00000000000000000000000011001111 $
#415
1!
b11111110 #
#416
0!
b11001111 "
b00000000000000000000000011010000 $
#417
1!
b11111111 #
#418
0!
b11010000 "
b00000000000000000000000011010001 $
#419
1!
b00000000 #
#420
0!
b11010001 "
b00000000000000000000000011010010 $
#421
1!
b00000001 #
#422
0!
b11010010 "
b00000000000000000000000011010011 $
#423
1!
b00000010 #
#424
0!
b11010011 "
b00000000000000000000000011010100 $
#425
1!
b00000011 #
#426
0!
b11010100 "
b00000000000000000000000011010101 $
#427
1!
b11111100 #
#428
0!
b11010101 "
b00000000000000000000000011010110 $
#429
1!
b11111101 #
#430
0!
b11010110 "
b00000000000000000000000011010111 $
#431
1!
b11111110 #
#432
0!
b11010111 "
b00000000000000000000000011011000 $
#433
1!
b11111111 #
#434
0!
b11011000 "
b00000000000000000000000011011001 $
#435
1!
b00000000 #
#436
0!
b11011001 "
b00000000000000000000000011011010 $
#437
1!
b00000001 #
#438
0!
b11011010 "
b00000000000000000000000011011011 $
#439
1!
b00000010 #
#440
0!
b11011011 "
b00000000000000000000000011011100 $
#441
1!
b00000011 #
#442
0!
b11011100 "
b00000000000000000000000011011101 $
#443
1!
b11111100 #
#444
0!
b11011101 "
b00000000000000000000000011011110 $
#445
1!
b11111101 #
#446
0!
b11011110 "
b00000000000000000000000011011111 $
#447
1!
b11111110 #
#448
0!
b11011111 "
b00000000000000000000000011100000 $
#449
1!
b11111111 #
#450
0!
b11100000 "
b00000000000000000000000011100001 $
#451
1!
b00000000 #
#452
0!
b11100001 "
b00000000000000000000000011100010 $
#453
1!
b00000001 #
#454
0!
b11100010 "
b00000000000000000000000011100011 $
#455
1!
b00000010 #
#456
0!
b11100011 "
b00000000000000000000000011100100 $
#457
1!
b00000011 #
#458
0!
b11100100 "
b00000000000000000000000011100101 $
#459
1!
b11111100 #
#460
0!
b11100101 "
b00000000000000000000000011100110 $
#461
1!
b11111101 #
#462
0!
b11100110 "
b00000000000000000000000011100111 $
#463
1!
b11111110 #
#464
0!
b11100111 "
b00000000000000000000000011101000 $
#465
1!
b11111111 #
#466
0!
b11101000 "
b00000000000000000000000011101001 $
#467
1!
b00000000 #
#468
0!
b11101001 "
b00000000000000000000000011101010 $
#469
1!
b00000001 #
#470
0!
b11101010 "
b00000000000000000000000011101011 $
#471
1!
b00000010 #
#472
0!
b11101011 "
b00000000000000000000000011101100 $
#473
1!
b00000011 #
#474
0!
b11101100 "
b00000000000000000000000011101101 $
#475
1!
b11111100 #
#476
0!
b11101101 "
b00000000000000000000000011101110 $
#477
1!
b11111101 #
#478
0!
b11101110 "
b00000000000000000000000011101111 $
#479
1!
b11111110 #
#480
0!
b11101111 "
b00000000000000000000000011110000 $
#481
1!
b11111111 #
#482
0!
b11110000 "
b00000000000000000000000011110001 $
#483
1!
b00000000 #
#484
0!
b11110001 "
b00000000000000000000000011110010 $
#485
1!
b00000001 #
#486
0!
b11110010 "
b00000000000000000000000011110011 $
#487
1!
b00000010 #
#488
0!
b11110011 "
b00000000000000000000000011110100 $
#489
1!
b00000011 #
#490
0!
b11110100 "
b00000000000000000000000011110101 $
#491
1!
b11111100 #
#492
0!
b11110101 "
b00000000000000000000000011110110 $
#493
1!
b11111101 #
#494
0!
b11110110 "
b00000000000000000000000011110111 $
#495
1!
b11111110 #
#496
0!
b11110111 "
b00000000000000000000000011111000 $
#497
1!
b11111111 #
#498
0!
b11111000 "
b00000000000000000000000011111001 $
#499
1!
b00000000 #
#500
0!
b11111001 "
b00000000000000000000000011111010 $
#501
1!
b00000001 #
#502
0!
b11111010 "
b00000000000000000000000011111011 $
#503
1!
b00000010 #
#504
0!
b11111011 "
b00000000000000000000000011111100 $
#505
1!
b00000011 #
#506
0!
b11111100 "
b00000000000000000000000011111101 $
#507
1!
b11111100 #
#508
0!
b11111101 "
b00000000000000000000000011111110 $
#509
1!
b11111101 #
#510
0!
b11111110 "
b00000000000000000000000011111111 $
#511
1!
b11111110 #
#512
0!
b11111111 "
b00000000000000000000000100000000 $
#513
1!
b11111111 #
#514
0!
b00000000 "
b00000000000000000000000100000001 $
#515
1!
b00000000 #
#516
0!
b00000001 "
b00000000000000000000000100000010 $
#517
1!
b00000001 #
#518
0!
b00000010 "
b00000000000000000000000100000011 $
#519
1!
b00000010 #
#520
0!
b00000011 "
b00000000000000000000000100000100 $
#521
1!
b00000011 #
#522
0!
b00000100 "
b00000000000000000000000100000101 $
#523
1!
b11111100 #
#524
0!
b00000101 "
b00000000000000000000000100000110 $
#525
1!
b11111101 #
#526
0!
b00000110 "
b00000000000000000000000100000111 $
#527
1!
b11111110 #
#528
0!
b00000111 "
b00000000000000000000000100001000 $
#529
1!
b11111111 #
#530
0!
b00001000 "
b00000000000000000000000100001001 $
#531
1!
b00000000 #
#532
0!
b00001001 "
b00000000000000000000000100001010 $
#533
1!
b00000001 #
#534
0!
b00001010 "
b00000000000000000000000100001011 $
#535
1!
b00000010 #
#536
0!
b00001011 "
b00000000000000000000000100001100 $
#537
1!
b00000011 #
#538
0!
b00001100 "
b00000000000000000000000100001101 $
#539
1!
b11111100 #
#540
0!
b00001101 "
b00000000000000000000000100001110 $
#541
1!
b11111101 #
#542
0!
b00001110 "
b00000000000000000000000100001111 $
#543
1!
b11111110 #
#544
0!
b00001111 "
b00000000000000000000000100010000 $
#545
1!
b11111111 #
#546
0!
b00010000 "
b00000000000000000000000100010001 $
#547
1!
b00000000 #
#548
0!
b00010001 "
b00000000000000000000000100010010 $
#549
1!
b00000001 #
#550
0!
b00010010 "
b00000000000000000000000100010011 $
#551
1!
b00000010 #
#552
0!
b00010011 "
b00000000000000000000000100010100 $
#553
1!
b00000011 #
#554
0!
b00010100 "
b00000000000000000000000100010101 $
#555
1!
b11111100 #
#556
0!
b00010101 "
b00000000000000000000000100010110 $
#557
1!
b11111101 #
#558
0!
b00010110 "
b00000000000000000000000100010111 $
#559
1!
b11111110 #
#560
0!
b00010111 "
b00000000000000000000000100011000 $
#561
1!
b11111111 #
#562
0!
b00011000 "
b00000000000000000000000100011001 $
#563
1!
b00000000 #
#564
0!
b00011001 "
b00000000000000000000000100011010 $
#565
1!
b00000001 #
#566
0!
b00011010 "
b00000000000000000000000100011011 $
#567
1!
b00000010 #
#568
0!
b00011011 "
b00000000000000000000000100011100 $
#569
1!
b00000011 #
#570
0!
b00011100 "
b00000000000000000000000100011101 $
#571
1!
b11111100 #
#572
0!
b00011101 "
b00000000000000000000000100011110 $
#573
1!
b11111101 #
#574
0!
b00011110 "
b00000000000000000000000100011111 $
#575
1!
b11111110 #
#576
0!
b00011111 "
b00000000000000000000000100100000 $
#577
1!
b11111111 #
#578
0!
b00100000 "
b00000000000000000000000100100001 $
#579
1!
b00000000 #
#580
0!
b00100001 "
b00000000000000000000000100100010 $
#581
1!
b00000001 #
#582
0!
b00100010 "
b00000000000000000000000100100011 $
#583
1!
b00000010 #
#584
0!
b00100011 "
b00000000000000000000000100100100 $
#585
1!
b00000011 #
#586
0!
b00100100 "
b00000000000000000000000100100101 $
#587
1!
b11111100 #
#588
0!
b00100101 "
b00000000000000000000000100100110 $
#589
1!
b11111101 #
#590
0!
b00100110 "
b00000000000000000000000100100111 $
#591
1!
b11111110 #
#592
0!
b00100111 "
b00000000000000000000000100101000 $
#593
1!
b11111111 #
#594
0!
b00101000 "
b00000000000000000000000100101001 $
#595
1!
b00000000 #
#596
0!
b00101001 "
b00000000000000000000000100101010 $
#597
1!
b00000001 #
#598
0!
b00101010 "
b00000000000000000000000100101011 $
#599
1!
b00000010 #
#600
0!
b00101011 "
b00000000000000000000000100101100 $
#601
1!
b00000011 #
#602
0!
b00101100 "
b00000000000000000000000100101101 $
#603
1!
b11111100 #
#604
0!
b00101101 "
b00000000000000000000000100101110 $
#605
1!
b11111101 #
#606
0!
b00101110 "
b00000000000000000000000100101111 $
#607
1!
b11111110 #
#608
0!
b00101111 "
b00000000000000000000000100110000 $
#609
1!
b11111111 #
#610
0!
b00110000 "
b00000000000000000000000100110001 $
#611
1!
b00000000 #
#612
0!
b00110001 "
b00000000000000000000000100110010 $
#613
1!
b00000001 #
#614
0!
b00110010 "
b00000000000000000000000100110011 $
#615
1!
b00000010 #
#616
0!
b00110011 "
b00000000000000000000000100110100 $
#617
1!
b00000011 #
#618
0!
b00110100 "
b00000000000000000000000100110101 $
#619
1!
b11111100 #
#620
0!
b00110101 "
b00000000000000000000000100110110 $
#621
1!
b11111101 #
#622
0!
b00110110 "
b00000000000000000000000100110111 $
#623
1!
b11111110 #
#624
0!
b00110111 "
b00000000000000000000000100111000 $
#625
1!
b11111111 #
#626
0!
b00111000 "
b00000000000000000000000100111001 $
#627
1!
b00000000 #
#628
0!
b00111001 "
b00000000000000000000000100111010 $
#629
1!
b00000001 #
#630
0!
b00111010 "
b00000000000000000000000100111011 $
#631
1!
b00000010 #
#632
0!
b00111011 "
b00000000000000000000000100111100 $
#633
1!
b00000011 #
#634
0!
b00111100 "
b00000000000000000000000100111101 $
#635
1!
b11111100 #
#636
0!
b00111101 "
b00000000000000000000000100111110 $
#637
1!
b11111101 #
#638
0!
b00111110 "
b00000000000000000000000100111111 $
#639
1!
b11111110 #
#640
0!
b00111111 "
b00000000000000000000000101000000 $
#641
1!
b11111111 #
#642
0!
b01000000 "
b00000000000000000000000101000001 $
#643
1!
b00000000 #
#644
0!
b01000001 "
b00000000000000000000000101000010 $
#645
1!
b00000001 #
#646
0!
b01000010 "
b00000000000000000000000101000011 $
#647
1!
b00000010 #
#648
0!
b01000011 "
b00000000000000000000000101000100 $
#649
1!
b00000011 #
#650
0!
b01000100 "
b00000000000000000000000101000101 $
#651
1!
b11111100 #
#652
0!
b01000101 "
b00000000000000000000000101000110 $
#653
1!
b11111101 #
#654
0!
b01000110 "
b00000000000000000000000101000111 $
#655
1!
b11111110 #
#656
0!
b01000111 "
b00000000000000000000000101001000 $
#657
1!
b11111111 #
#658
0!
b01001000 "
b00000000000000000000000101001001 $
#659
1!
b00000000 #
#660
0!
b01001001 "
b00000000000000000000000101001010 $
#661
1!
b00000001 #
#662
0!
b01001010 "
b00000000000000000000000101001011 $
#663
1!
b00000010 #
#664
0!
b01001011 "
b00000000000000000000000101001100 $
#665
1!
b00000011 #
#666
0!
b01001100 "
b00000000000000000000000101001101 $
#667
1!
b11111100 #
#668
0!
b01001101 "
b00000000000000000000000101001110 $
#669
1!
b11111101 #
#670
0!
b01001110 "
b00000000000000000000000101001111 $
#671
1!
b11111110 #
#672
0!
b01001111 "
b00000000000000000000000101010000 $
#673
1!
b11111111 #
#674
0!
b01010000 "
b00000000000000000000000101010001 $
#675
1!
b00000000 #
#676
0!
b01010001 "
b00000000000000000000000101010010 $
#677
1!
b00000001 #
#678
0!
b01010010 "
b00000000000000000000000101010011 $
#679
1!
b00000010 #
#680
0!
b01010011 "
b00000000000000000000000101010100 $
#681
1!
b00000011 #
#682
0!
b01010100 "
b00000000000000000000000101010101 $
#683
1!
b11111100 #
#684
0!
b01010101 "
b00000000000000000000000101010110 $
#685
1!
b11111101 #
#686
0!
b01010110 "
b00000000000000000000000101010111 $
#687
1!
b11111110 #
#688
0!
b01010111 "
b00000000000000000000000101011000 $
#689
1!
b11111111 #
#690
0!
b01011000 "
b00000000000000000000000101011001 $
#691
1!
b00000000 #
#692
0!
b01011001 "
b00000000000000000000000101011010 $
#693
1!
b00000001 #
#694
0!
b01011010 "
b00000000000000000000000101011011 $
#695
1!
b00000010 #
#696
0!
b01011011 "
b00000000000000000000000101011100 $
#697
1!
b00000011 #
#698
0!
b01011100 "
b00000000000000000000000101011101 $
#699
1!
b11111100 #
#700
0!
b01011101 "
b00000000000000000000000101011110 $
#701
1!
b11111101 #
